mkdocs_apicall_plugin/__init__.py
mkdocs_apicall_plugin/abstract.py
mkdocs_apicall_plugin/curl.py
mkdocs_apicall_plugin/javascript.py
mkdocs_apicall_plugin/main.py
mkdocs_apicall_plugin/python.py
mkdocs_apicall_plugin-0.3.0.dist-info/METADATA
mkdocs_apicall_plugin-0.3.0.dist-info/WHEEL
mkdocs_apicall_plugin-0.3.0.dist-info/entry_points.txt
mkdocs_apicall_plugin-0.3.0.dist-info/licenses/LICENSE
mkdocs_apicall_plugin-0.3.0.dist-info/RECORD
