Metadata-Version: 2.4
Name: mkdocs-apicall-plugin
Version: 0.3.0
Summary: Auto-generate code samples to make API calls
Author-email: Alban Siffer <31479857+asiffer@users.noreply.github.com>
License: Apache-2.0
License-File: LICENSE
Requires-Python: >=3.9
Requires-Dist: black>=24.3.0
Requires-Dist: mkdocs-material>=9.1.4
Requires-Dist: mkdocs>=1.4.2
Requires-Dist: pygments>=2.14.0
